DIAL/Address.py
DIAL/Color.py
DIAL/Error.py
DIAL/Message.py
DIAL/ReadOnlyDict.py
DIAL/Scheduler.py
DIAL/Simulator.py
DIAL/State.py
DIAL/Topology.py
DIAL/__init__.py
DIAL/API/API.py
DIAL/API/ControlEndpoints.py
DIAL/API/MessageEndpoints.py
DIAL/API/SSL.py
DIAL/API/StateEndpoints.py
DIAL/API/TopologyEndpoints.py
DIAL/API/web/index.html
DIAL/API/web/package-lock.json
DIAL/API/web/package.json
DIAL/API/web/assets/svg/angle-left.svg
DIAL/API/web/assets/svg/angle-right.svg
DIAL/API/web/assets/svg/close.svg
DIAL/API/web/assets/svg/end.svg
DIAL/API/web/assets/svg/next.svg
DIAL/API/web/assets/svg/pause.svg
DIAL/API/web/assets/svg/play.svg
DIAL/API/web/assets/svg/previous.svg
DIAL/API/web/assets/svg/start.svg
DIAL/API/web/favicons/android-chrome-192x192.png
DIAL/API/web/favicons/android-chrome-512x512.png
DIAL/API/web/favicons/apple-touch-icon.png
DIAL/API/web/favicons/favicon-16x16.png
DIAL/API/web/favicons/favicon-32x32.png
DIAL/API/web/favicons/favicon.ico
DIAL/API/web/favicons/icon.svg
DIAL/API/web/favicons/site.webmanifest
DIAL/API/web/libraries/lit-core.js
DIAL/API/web/libraries/sortable.js
DIAL/API/web/libraries/victor.js
DIAL/API/web/libraries/vis.js
DIAL/API/web/libraries/codemirror/codemirror.min.css
DIAL/API/web/libraries/codemirror/codemirror.min.js
DIAL/API/web/libraries/codemirror/dracula.min.css
DIAL/API/web/libraries/codemirror/javascript.min.js
DIAL/API/web/libraries/codemirror/sublime.min.js
DIAL/API/web/libraries/codemirror_old/lang-json.js
DIAL/API/web/libraries/shoelace/shoelace.js
DIAL/API/web/libraries/shoelace/themes/light.css
DIAL/API/web/node_modules/csstype/LICENSE
DIAL/API/web/node_modules/csstype/README.md
DIAL/API/web/node_modules/csstype/index.d.ts
DIAL/API/web/node_modules/csstype/index.js.flow
DIAL/API/web/node_modules/csstype/package.json
DIAL/API/web/node_modules/lit/LICENSE
DIAL/API/web/node_modules/lit/README.md
DIAL/API/web/node_modules/lit/async-directive.d.ts
DIAL/API/web/node_modules/lit/async-directive.d.ts.map
dial_simulator-0.1.2b0.dist-info/LICENSE.md
dial_simulator-0.1.2b0.dist-info/METADATA
dial_simulator-0.1.2b0.dist-info/WHEEL
dial_simulator-0.1.2b0.dist-info/top_level.txt
dial_simulator-0.1.2b0.dist-info/RECORD
