Metadata-Version: 2.1
Name: dial-simulator
Version: 0.1.2b0
Summary: DIAL is a framework for simulating and visualizing distributed algorithms in Python.
Author: DasenB
License: This project is licensed under Creative Commons BY-NC-SA 4.0
Project-URL: Source Code, https://github.com/DasenB/DIAL
Keywords: distributed system,distributed algorithm,simulator,visualization
Classifier: Topic :: System :: Distributed Computing
Classifier: Topic :: Scientific/Engineering :: Visualization
Requires-Python: >=3.12
License-File: LICENSE.md
Requires-Dist: flask >=2.3.3
Requires-Dist: flask-cors >=4.0.0
Requires-Dist: numpy >=1.26.2
Requires-Dist: cryptography >=41.0.7
